{"id":"316d99ad-bd50-49e3","name":"girlLevel","scene":[{"id":"5f329e7e-c422-4bff","needsHitTest":false,"label":"rootGirlLevel","meshId":"","projectId":"","isText":false,"text":"","textSpacing":-1,"needsTrigger":false,"triggerRadius":0.2,"mouseHitID":"","needsMouseHit":false,"position":[0,0,0],"rotation":[0,0,0,1],"hitTriggerItem":0,"lockScaleXY":false,"dropShadow":true,"isTransparent":false,"needsTransShading":false,"postLight":false,"textColor":[0,0,0,1],"parentID":"70ac33a3-b363-4611"},{"id":"b5963f14-1661-4d1a","needsHitTest":true,"label":"floor","meshId":"e0a4c2d8-b095-4b02-ae97-8c0dc71fc3eb","projectId":"f30630be-711b-4baf-993a-c15ca85d5827","isText":false,"text":"","textSpacing":-1,"needsTrigger":false,"triggerRadius":0.2,"mouseHitID":"","needsMouseHit":false,"position":[22.393420618580702,0,0],"rotation":[0,0,0,1],"hitTriggerItem":0,"lockScaleXY":false,"dropShadow":false,"isTransparent":false,"needsTransShading":false,"postLight":false,"textColor":[0,0,0,1],"model":"e0a4c2d8-b095-4b02-ae97-8c0dc71fc3eb","scale":[1054.791902159606,0.14999999999999933,1127.6671765595358],"parentID":"5f329e7e-c422-4bff"},{"id":"1890c65e-eaca-4b9e","needsHitTest":false,"label":"girl","meshId":"442bd033-635e-43a0","projectId":"13ede288-eb43-4a8a","isText":false,"text":"","textSpacing":-1,"needsTrigger":true,"triggerRadius":1.0239843750000008,"mouseHitID":"","needsMouseHit":false,"position":[0,0.2944013259795406,0],"rotation":[0,0,0,1],"hitTriggerItem":9,"lockScaleXY":true,"dropShadow":true,"isTransparent":false,"needsTransShading":false,"postLight":false,"textColor":[0,0,0,1],"model":"442bd033-635e-43a0","scale":[1.4,1.4,5.142500000000002],"parentID":"5f329e7e-c422-4bff"},{"id":"6e08c625-3481-4230","needsHitTest":false,"label":"girlHead","meshId":"1982b011-139e-4cd5","projectId":"13ede288-eb43-4a8a","isText":false,"text":"","textSpacing":-1,"needsTrigger":false,"triggerRadius":0.2,"mouseHitID":"","needsMouseHit":false,"position":[-0.08361414608860984,0.3496829751257,0.06290406810784654],"rotation":[-0.0023955650576620653,-0.08339109772345452,0.02901717554615393,0.9960914564495851],"hitTriggerItem":0,"lockScaleXY":true,"dropShadow":true,"isTransparent":false,"needsTransShading":false,"postLight":false,"textColor":[0,0,0,1],"model":"1982b011-139e-4cd5","scale":[1.3,1.3,3.4124609375000015],"parentID":"1890c65e-eaca-4b9e"},{"id":"c4decd48-6f76-44e4","needsHitTest":false,"label":"myNewObject_2","meshId":"970ad9fe-b2e3-41ce","projectId":"13ede288-eb43-4a8a","isText":false,"text":"","textSpacing":-1,"needsTrigger":false,"triggerRadius":0.2,"mouseHitID":"","needsMouseHit":false,"position":[-0.14974728502968515,0.11353199478557019,-0.02683941759029325],"rotation":[0,0,0,1],"hitTriggerItem":0,"lockScaleXY":false,"dropShadow":true,"isTransparent":false,"needsTransShading":false,"postLight":false,"textColor":[0,0,0,1],"model":"970ad9fe-b2e3-41ce","scale":[2.5775271879082022,2.516981450903902,1],"parentID":"6e08c625-3481-4230"},{"id":"b97fb5a2-6689-4330","needsHitTest":false,"label":"myNewObject_3","meshId":"12171c91-c802-41f9","projectId":"13ede288-eb43-4a8a","isText":false,"text":"","textSpacing":-1,"needsTrigger":false,"triggerRadius":0.2,"mouseHitID":"","needsMouseHit":false,"position":[-0.22056070619227158,0.10063264307860309,-0.04571993283225945],"rotation":[0.0001888430845189904,-0.003525618386571059,-0.053486104839066746,0.9985623520554068],"hitTriggerItem":0,"lockScaleXY":true,"dropShadow":true,"isTransparent":false,"needsTransShading":false,"postLight":false,"textColor":[0,0,0,1],"model":"12171c91-c802-41f9","scale":[1.4,1.4,1],"parentID":"6e08c625-3481-4230"},{"id":"57c1ccc8-9dd6-4726","needsHitTest":false,"label":"eyeLeft","meshId":"489eef5e-18e4-416b","projectId":"13ede288-eb43-4a8a","isText":false,"text":"","textSpacing":-1,"needsTrigger":false,"triggerRadius":0.2,"mouseHitID":"","needsMouseHit":false,"position":[-0.09901558735176003,0.08601927856863767,-0.006800312835466976],"rotation":[0,0,0,1],"hitTriggerItem":0,"lockScaleXY":false,"dropShadow":true,"isTransparent":false,"needsTransShading":false,"postLight":false,"textColor":[0,0,0,1],"model":"489eef5e-18e4-416b","scale":[1.645965632120822,1.355920646791604,1],"parentID":"6e08c625-3481-4230"},{"id":"e654a1b7-5d9e-4375","needsHitTest":false,"label":"eyeLeft_2","meshId":"489eef5e-18e4-416b","projectId":"13ede288-eb43-4a8a","isText":false,"text":"","textSpacing":-1,"needsTrigger":false,"triggerRadius":0.2,"mouseHitID":"","needsMouseHit":false,"position":[-0.2293865690635139,0.07993614008620165,0.010289439721519175],"rotation":[0,0,0,1],"hitTriggerItem":0,"lockScaleXY":false,"dropShadow":true,"isTransparent":false,"needsTransShading":false,"postLight":false,"textColor":[0,0,0,1],"model":"489eef5e-18e4-416b","scale":[1.303413891326845,1.3435269133415528,1],"parentID":"6e08c625-3481-4230"},{"id":"10ceef26-66ba-4927","needsHitTest":false,"label":"myNewObject_4","meshId":"8b8a9d32-b291-4173","projectId":"13ede288-eb43-4a8a","isText":false,"text":"","textSpacing":-1,"needsTrigger":false,"triggerRadius":0.2,"mouseHitID":"","needsMouseHit":false,"position":[0.03331083065317186,0.38992155907140524,0.032678289831905794],"rotation":[-0.02158853909928455,0,0,0.9997669403313748],"hitTriggerItem":0,"lockScaleXY":true,"dropShadow":true,"isTransparent":false,"needsTransShading":false,"postLight":false,"textColor":[0,0,0,1],"model":"8b8a9d32-b291-4173","scale":[1.4,1.4,1],"parentID":"1890c65e-eaca-4b9e"},{"id":"d35e1c09-1e91-4c59","needsHitTest":false,"label":"wing","meshId":"0fa59e7e-5c3a-4ec0","projectId":"13ede288-eb43-4a8a","isText":false,"text":"","textSpacing":-1,"needsTrigger":false,"triggerRadius":0.2,"mouseHitID":"","needsMouseHit":false,"position":[-0.0390129172620608,0.43964693397458243,-0.04088159935468383],"rotation":[-0.13415558379591808,0.09808192603207279,0.013345013243257356,0.9860041205511022],"hitTriggerItem":0,"lockScaleXY":false,"dropShadow":true,"isTransparent":false,"needsTransShading":false,"postLight":false,"textColor":[0,0,0,1],"model":"0fa59e7e-5c3a-4ec0","scale":[1.4,1,1],"parentID":"1890c65e-eaca-4b9e"},{"id":"83f80b4b-3ad6-4635","needsHitTest":false,"label":"wing_2","meshId":"0fa59e7e-5c3a-4ec0","projectId":"13ede288-eb43-4a8a","isText":false,"text":"","textSpacing":-1,"needsTrigger":false,"triggerRadius":0.2,"mouseHitID":"","needsMouseHit":false,"position":[0.03607920242102165,0.3959785734967368,0],"rotation":[0.016579604168297266,-0.031624594272897405,0.0005246579029144927,0.9993621598283489],"hitTriggerItem":0,"lockScaleXY":false,"dropShadow":true,"isTransparent":false,"needsTransShading":false,"postLight":false,"textColor":[0,0,0,1],"model":"0fa59e7e-5c3a-4ec0","scale":[1.4,1,1],"parentID":"1890c65e-eaca-4b9e"},{"id":"44546286-a28c-4865","needsHitTest":false,"label":"myNewObject_5","meshId":"37bbe152-b525-4981","projectId":"13ede288-eb43-4a8a","isText":false,"text":"","textSpacing":-1,"needsTrigger":false,"triggerRadius":0.2,"mouseHitID":"","needsMouseHit":false,"position":[0,0.27610609418734233,-0.056258804856470945],"rotation":[0,0.1466224304070792,0,0.98919253075502],"hitTriggerItem":0,"lockScaleXY":false,"dropShadow":true,"isTransparent":false,"needsTransShading":false,"postLight":false,"textColor":[0,0,0,1],"model":"37bbe152-b525-4981","scale":[1.4,1,1],"parentID":"1890c65e-eaca-4b9e"},{"id":"86509b4a-d8a2-4864","needsHitTest":false,"label":"legR","meshId":"68dbc709-4800-4c30","projectId":"13ede288-eb43-4a8a","isText":false,"text":"","textSpacing":-1,"needsTrigger":false,"triggerRadius":0.2,"mouseHitID":"","needsMouseHit":false,"position":[-0.07486781109575719,0.2890332954259275,0],"rotation":[0,0,0,1],"hitTriggerItem":0,"lockScaleXY":true,"dropShadow":true,"isTransparent":false,"needsTransShading":false,"postLight":false,"textColor":[0,0,0,1],"model":"68dbc709-4800-4c30","scale":[1.4,1.4,1],"parentID":"5f329e7e-c422-4bff"},{"id":"299ea959-3462-4763","needsHitTest":false,"label":"legL","meshId":"68dbc709-4800-4c30","projectId":"13ede288-eb43-4a8a","isText":false,"text":"","textSpacing":-1,"needsTrigger":false,"triggerRadius":0.2,"mouseHitID":"","needsMouseHit":false,"position":[0.08094329252557114,0.2886892063626615,0],"rotation":[0,0,0,1],"hitTriggerItem":0,"lockScaleXY":true,"dropShadow":true,"isTransparent":false,"needsTransShading":false,"postLight":false,"textColor":[0,0,0,1],"model":"68dbc709-4800-4c30","scale":[1.4,1.4,1],"parentID":"5f329e7e-c422-4bff"}],"animations":[]}